{
  "id": "7",
  "name": "Upper Charles Cut to Dam w gates - Upper Charles - Cut to Dam",
  "country": "United States",
  "center_lat": 42.362358,
  "center_lon": -71.245785,
  "distance_m": 2726,
  "notes": "",
  "status": "established",
  "submitted_by": "migrated from Rowsandall",
  "polygons": [
    {
      "name": "Start",
      "order": 0,
      "points": [
        {
          "lat": 42.354136008567,
          "lon": -71.2556325601296
        },
        {
          "lat": 42.3536167831287,
          "lon": -71.2548176050472
        },
        {
          "lat": 42.3538924684825,
          "lon": -71.2546466754058
        },
        {
          "lat": 42.3543392074363,
          "lon": -71.2553385381592
        },
        {
          "lat": 42.354136008567,
          "lon": -71.2556325601296
        }
      ]
    },
    {
      "name": "Gate 1",
      "order": 1,
      "points": [
        {
          "lat": 42.3554160904067,
          "lon": -71.2535851779107
        },
        {
          "lat": 42.3550448258438,
          "lon": -71.252606270634
        },
        {
          "lat": 42.355247322293,
          "lon": -71.2524734718732
        },
        {
          "lat": 42.3556440249259,
          "lon": -71.253450192549
        },
        {
          "lat": 42.3554160904067,
          "lon": -71.2535851779107
        }
      ]
    },
    {
      "name": "Gate 2",
      "order": 2,
      "points": [
        {
          "lat": 42.3589577308112,
          "lon": -71.2521215047803
        },
        {
          "lat": 42.3585569588595,
          "lon": -71.2509897901817
        },
        {
          "lat": 42.3588828784111,
          "lon": -71.2508961366052
        },
        {
          "lat": 42.3593174042369,
          "lon": -71.2518772693738
        },
        {
          "lat": 42.3589577308112,
          "lon": -71.2521215047803
        }
      ]
    },
    {
      "name": "Gate 3",
      "order": 3,
      "points": [
        {
          "lat": 42.3624989486946,
          "lon": -71.249332943361
        },
        {
          "lat": 42.3614161956683,
          "lon": -71.2487525187454
        },
        {
          "lat": 42.3616849563082,
          "lon": -71.2483142330764
        },
        {
          "lat": 42.3626654210578,
          "lon": -71.2489494540085
        },
        {
          "lat": 42.3624989486946,
          "lon": -71.249332943361
        }
      ]
    },
    {
      "name": "Gate 4",
      "order": 4,
      "points": [
        {
          "lat": 42.3624346024172,
          "lon": -71.2462632616485
        },
        {
          "lat": 42.3619332052368,
          "lon": -71.2454331538001
        },
        {
          "lat": 42.3622378438381,
          "lon": -71.2450266458227
        },
        {
          "lat": 42.362748853588,
          "lon": -71.2459397890705
        },
        {
          "lat": 42.3624346024172,
          "lon": -71.2462632616485
        }
      ]
    },
    {
      "name": "Gate 5",
      "order": 5,
      "points": [
        {
          "lat": 42.3648011147685,
          "lon": -71.245846489859
        },
        {
          "lat": 42.3644365990183,
          "lon": -71.2449685268198
        },
        {
          "lat": 42.3649360375315,
          "lon": -71.2448302366589
        },
        {
          "lat": 42.3652572771209,
          "lon": -71.2457871095916
        },
        {
          "lat": 42.3648011147685,
          "lon": -71.245846489859
        }
      ]
    },
    {
      "name": "Gate 6",
      "order": 6,
      "points": [
        {
          "lat": 42.3681368049989,
          "lon": -71.2447501686996
        },
        {
          "lat": 42.3677956965692,
          "lon": -71.2439824462268
        },
        {
          "lat": 42.3680501902699,
          "lon": -71.2438514360017
        },
        {
          "lat": 42.3683769574015,
          "lon": -71.2446604457239
        },
        {
          "lat": 42.3681368049989,
          "lon": -71.2447501686996
        }
      ]
    },
    {
      "name": "Gate 7",
      "order": 7,
      "points": [
        {
          "lat": 42.3710894731929,
          "lon": -71.2414228630543
        },
        {
          "lat": 42.3705725981634,
          "lon": -71.2408472496329
        },
        {
          "lat": 42.3707944723287,
          "lon": -71.2405627350691
        },
        {
          "lat": 42.3713457932622,
          "lon": -71.2412060373554
        },
        {
          "lat": 42.3710894731929,
          "lon": -71.2414228630543
        }
      ]
    },
    {
      "name": "Finish",
      "order": 8,
      "points": [
        {
          "lat": 42.3726207667011,
          "lon": -71.2373126359633
        },
        {
          "lat": 42.3731623748746,
          "lon": -71.237463477181
        },
        {
          "lat": 42.3731317754161,
          "lon": -71.2377109875848
        },
        {
          "lat": 42.3725826700644,
          "lon": -71.2374646568404
        },
        {
          "lat": 42.3726207667011,
          "lon": -71.2373126359633
        }
      ]
    }
  ]
}